umat_kit/__init__.py
umat_kit/admin_config.py
umat_kit/cli.py
umat_kit/config.py
umat_kit/student_portal.py
umat_kit/api/api/__init__.py
umat_kit/api/api/academic_results_api.py
umat_kit/api/api/admin_api.py
umat_kit/api/api/api_manager.py
umat_kit/api/api/base_client.py
umat_kit/api/api/bills_payment_api.py
umat_kit/api/api/course_assessment_api.py
umat_kit/api/api/course_registration_api.py
umat_kit/api/api/email_update_api.py
umat_kit/api/api/login_api.py
umat_kit/api/api/profile_update_api.py
umat_kit/api/api/userinfo_api.py
umat_kit/scripts/__init__.py
umat_kit/scripts/activate_stu_email.py
umat_kit/scripts/confirm_results.json
umat_kit/scripts/confirmed_refs.json
umat_kit/scripts/gen_vle_logins.py
umat_kit/scripts/invalid_ref.json
umat_kit/scripts/login.py
umat_kit/scripts/non_user.json
umat_kit/scripts/password_generator.py
umat_kit/scripts/ref.json
umat_kit/scripts/ref_check_results.json
umat_kit/scripts/test_runner.py
umat_kit/scripts/umat_reference_analyzer.py
umat_kit/scripts/umat_reference_generator.py
umat_kit/scripts/user_info_results.json
umat_kit/scripts/userinfo.py
umat_kit/scripts/valid_ref.json
umat_kit/scripts/valid_user.json
umat_kit/scripts/validate_refs.py
umat_kit/utils/utils/__init__.py
umat_kit/utils/utils/crypto.py
umat_kit/utils/utils/logger.py
umat_kit/utils/utils/terminal_colors.py
umat_kit/utils/utils/validators.py
umat_kit-0.1.3.dist-info/licenses/LICENSE
umat_kit-0.1.3.dist-info/METADATA
umat_kit-0.1.3.dist-info/WHEEL
umat_kit-0.1.3.dist-info/entry_points.txt
umat_kit-0.1.3.dist-info/top_level.txt
umat_kit-0.1.3.dist-info/RECORD
