Metadata-Version: 2.4
Name: umat-kit
Version: 0.1.3
Summary: 🎓 Complete UMAT Student Portal Toolkit - API client, automated course assessment bot, CLI interface, and utilities for UMAT students
Author-email: kalculusGuy <umatkit@gmail.com>
License-Expression: MIT
Project-URL: Source, https://github.com/Odeneho-Calculus/UMaT-Kit
Project-URL: Tracker, https://github.com/Odeneho-Calculus/UMaT-Kit/issues
Keywords: umat,student-portal,api-client,course-assessment,automation,cli,education
Classifier: Development Status :: 5 - Production/Stable
Classifier: Intended Audience :: Education
Classifier: Intended Audience :: End Users/Desktop
Classifier: Intended Audience :: Developers
Classifier: Programming Language :: Python :: 3
Classifier: Programming Language :: Python :: 3 :: Only
Classifier: Programming Language :: Python :: 3.10
Classifier: Programming Language :: Python :: 3.11
Classifier: Programming Language :: Python :: 3.12
Classifier: Operating System :: OS Independent
Classifier: Topic :: Education
Classifier: Topic :: Internet :: WWW/HTTP :: Dynamic Content
Classifier: Topic :: Software Development :: Libraries :: Python Modules
Classifier: Topic :: Utilities
Classifier: Environment :: Console
Requires-Python: >=3.10
License-File: LICENSE
Requires-Dist: requests>=2.31.0
Requires-Dist: colorama>=0.4.6
Requires-Dist: rich>=13.7.0
Requires-Dist: python-dotenv>=1.0.0
Requires-Dist: pydantic>=2.5.0
Requires-Dist: sqlalchemy>=2.0.0
Requires-Dist: alembic>=1.13.0
Requires-Dist: psycopg2-binary>=2.9.0
Requires-Dist: pymongo>=4.6.0
Requires-Dist: redis>=5.0.0
Requires-Dist: cryptography>=41.0.0
Requires-Dist: PyJWT>=2.8.0
Requires-Dist: click>=8.1.0
Requires-Dist: tabulate>=0.9.0
Requires-Dist: email-validator>=2.1.0
Dynamic: license-file
